{
  "address1": "Praia de Botafogo, 186",
  "address2": "16th Floor Botafogo District",
  "city": "Rio De Janeiro",
  "state": "RJ",
  "country": "Brazil",
  "phone": "55 80 0810 8543",
  "website": "https://bravaenergia.com",
  "industry": "Oil & Gas E&P",
  "industryKey": "oil-gas-e-p",
  "industryDisp": "Oil & Gas E&P",
  "sector": "Energy",
  "sectorKey": "energy",
  "sectorDisp": "Energy",
  "longBusinessSummary": "Brava Energia S.A. engages in the exploration and production of oil and natural gas in Brazil. The company was formerly known as 3R Petroleum \u00d3leo e G\u00e1s S.A. and changed its name to Brava Energia S.A. in September 2024. The company was founded in 2010 and is headquartered in Rio De Janeiro, Brazil.",
  "companyOfficers": [
    {
      "maxAge": 1,
      "name": "Mr. Richard Kehrer Kovacs",
      "title": "CEO & Director",
      "exercisedValue": 0,
      "unexercisedValue": 0
    },
    {
      "maxAge": 1,
      "name": "Mr. Luiz  Felipe Carvalho",
      "title": "CFO & Chief Investor Relations Officer",
      "exercisedValue": 0,
      "unexercisedValue": 0
    },
    {
      "maxAge": 1,
      "name": "Mr. Jorge  Boeri",
      "title": "Onshore Operations Director & Member of Management Board",
      "exercisedValue": 0,
      "unexercisedValue": 0
    },
    {
      "maxAge": 1,
      "name": "Leandro Nonato Da Cunha",
      "title": "Accounting Manager",
      "exercisedValue": 0,
      "unexercisedValue": 0
    },
    {
      "maxAge": 1,
      "name": "Mr. Carlos Jose do Nascimento Travassos",
      "age": 57,
      "title": "Chief Offshore Operational Officer",
      "yearBorn": 1968,
      "exercisedValue": 0,
      "unexercisedValue": 0
    },
    {
      "maxAge": 1,
      "name": "Mr. Mauro Braz Rocha",
      "title": "Controller",
      "exercisedValue": 0,
      "unexercisedValue": 0
    }
  ],
  "executiveTeam": [],
  "maxAge": 86400,
  "priceHint": 2,
  "previousClose": 17.47,
  "open": 17.46,
  "dayLow": 16.38,
  "dayHigh": 17.53,
  "regularMarketPreviousClose": 17.47,
  "regularMarketOpen": 17.46,
  "regularMarketDayLow": 16.38,
  "regularMarketDayHigh": 17.53,
  "exDividendDate": 1714608000,
  "payoutRatio": 0.0,
  "beta": -0.053,
  "trailingPE": 5.5927153,
  "forwardPE": 4.0255113,
  "volume": 19092700,
  "regularMarketVolume": 19092700,
  "averageVolume": 9899901,
  "averageVolume10days": 11280820,
  "averageDailyVolume10Day": 11280820,
  "bid": 16.89,
  "ask": 16.92,
  "marketCap": 7846132736,
  "nonDilutedMarketCap": 7846132992,
  "fiftyTwoWeekLow": 13.29,
  "fiftyTwoWeekHigh": 23.7,
  "allTimeHigh": 51.58,
  "allTimeLow": 13.29,
  "priceToSalesTrailing12Months": 0.6750528,
  "fiftyDayAverage": 18.2154,
  "twoHundredDayAverage": 17.4978,
  "trailingAnnualDividendRate": 0.0,
  "trailingAnnualDividendYield": 0.0,
  "currency": "BRL",
  "tradeable": false,
  "enterpriseValue": 22924269568,
  "profitMargins": 0.12142,
  "floatShares": 431678056,
  "sharesOutstanding": 464543102,
  "heldPercentInsiders": 0.06999,
  "heldPercentInstitutions": 0.70602,
  "impliedSharesOutstanding": 464543102,
  "bookValue": 25.366,
  "priceToBook": 0.66585195,
  "lastFiscalYearEnd": 1767139200,
  "nextFiscalYearEnd": 1798675200,
  "mostRecentQuarter": 1767139200,
  "netIncomeToCommon": 1411224960,
  "trailingEps": 3.02,
  "forwardEps": 4.19574,
  "enterpriseToRevenue": 1.972,
  "enterpriseToEbitda": 6.098,
  "52WeekChange": -0.20704228,
  "SandP52WeekChange": 0.12811458,
  "quoteType": "EQUITY",
  "currentPrice": 16.89,
  "targetHighPrice": 30.0,
  "targetLowPrice": 17.0,
  "targetMeanPrice": 23.04167,
  "targetMedianPrice": 23.0,
  "recommendationMean": 1.83333,
  "recommendationKey": "buy",
  "numberOfAnalystOpinions": 12,
  "totalCash": 5604012032,
  "totalCashPerShare": 12.073,
  "ebitda": 3759394048,
  "totalDebt": 20688535552,
  "quickRatio": 1.146,
  "currentRatio": 1.422,
  "totalRevenue": 11622990848,
  "debtToEquity": 175.711,
  "revenuePerShare": 25.037,
  "returnOnAssets": 0.02863,
  "returnOnEquity": 0.12658,
  "grossProfits": 3061548032,
  "freeCashflow": 823872512,
  "operatingCashflow": 4871973888,
  "revenueGrowth": 0.307,
  "grossMargins": 0.2634,
  "ebitdaMargins": 0.32344002,
  "operatingMargins": -0.28193,
  "financialCurrency": "BRL",
  "symbol": "BRAV3.SA",
  "language": "en-US",
  "region": "US",
  "typeDisp": "Equity",
  "quoteSourceName": "Delayed Quote",
  "triggerable": false,
  "customPriceAlertConfidence": "LOW",
  "marketState": "CLOSED",
  "corporateActions": [],
  "regularMarketTime": 1774037484,
  "shortName": "BRAVA       ON      NM",
  "longName": "Brava Energia S.A.",
  "fullExchangeName": "S\u00e3o Paulo",
  "averageDailyVolume3Month": 9899901,
  "fiftyTwoWeekLowChange": 3.5999994,
  "fiftyTwoWeekLowChangePercent": 0.2708803,
  "fiftyTwoWeekRange": "13.29 - 23.7",
  "fiftyTwoWeekHighChange": -6.8100014,
  "fiftyTwoWeekHighChangePercent": -0.28734183,
  "fiftyTwoWeekChangePercent": -20.704227,
  "earningsTimestamp": 1778702400,
  "earningsTimestampStart": 1778702400,
  "earningsTimestampEnd": 1778702400,
  "earningsCallTimestampStart": 1773334800,
  "earningsCallTimestampEnd": 1773334800,
  "isEarningsDateEstimate": false,
  "epsTrailingTwelveMonths": 3.02,
  "epsForward": 4.19574,
  "epsCurrentYear": 2.726,
  "priceEpsCurrentYear": 6.195891,
  "fiftyDayAverageChange": -1.3254013,
  "fiftyDayAverageChangePercent": -0.072762676,
  "twoHundredDayAverageChange": -0.60780144,
  "twoHundredDayAverageChangePercent": -0.034735877,
  "sourceInterval": 15,
  "exchangeDataDelayedBy": 15,
  "prevName": "3R Petroleum \u00d3leo e G\u00e1s S.A.",
  "nameChangeDate": "2026-03-21",
  "averageAnalystRating": "1.8 - Buy",
  "cryptoTradeable": false,
  "exchange": "SAO",
  "messageBoardId": "finmb_243296553",
  "exchangeTimezoneName": "America/Sao_Paulo",
  "exchangeTimezoneShortName": "BRT",
  "gmtOffSetMilliseconds": -10800000,
  "market": "br_market",
  "esgPopulated": false,
  "regularMarketChangePercent": -3.3199768,
  "regularMarketPrice": 16.89,
  "hasPrePostMarketData": false,
  "firstTradeDateMilliseconds": 1605013200000,
  "regularMarketChange": -0.5799999,
  "regularMarketDayRange": "16.38 - 17.53",
  "trailingPegRatio": null
}