{
  "address1": "Avenida Barbacena, 1200",
  "city": "Belo Horizonte",
  "state": "MG",
  "zip": "30190-131",
  "country": "Brazil",
  "phone": "51 31 3506 5024",
  "website": "https://www.cemig.com.br",
  "industry": "Utilities - Diversified",
  "industryKey": "utilities-diversified",
  "industryDisp": "Utilities - Diversified",
  "sector": "Utilities",
  "sectorKey": "utilities",
  "sectorDisp": "Utilities",
  "longBusinessSummary": "Companhia Energ\u00e9tica de Minas Gerais - CEMIG, through its subsidiaries, engages in the generation, transmission, distribution, and sale of energy in Brazil. As of December 31, 2024, the company operated 36 hydro plants with a total capacity of 4,449.0 MW, 2 wind farms with a total capacity of 70.8 MW, and 10 photovoltaic power stations with a total capacity of 158.99 MW; 357,044 miles of distribution lines; and 4,754 miles of transmission lines. It is also involved in the acquisition, transportation, and distribution of gas and its sub products and derivatives; sale and trading of energy; construction, implementation, operation and maintenance of electricity transmission; marketing and intermediation of energy-related business; installation, operation, maintenance and rental of solar plants; and distributed generation, account services, cogeneration, energy efficiency, and supply and storage management activities. The company was incorporated in 1952 and is headquartered in Belo Horizonte, Brazil.",
  "fullTimeEmployees": 5320,
  "companyOfficers": [
    {
      "maxAge": 1,
      "name": "Mr. Reynaldo Passanezi Filho",
      "age": 60,
      "title": "CEO, President & Member of Executive Board",
      "yearBorn": 1965,
      "exercisedValue": 0,
      "unexercisedValue": 0
    },
    {
      "maxAge": 1,
      "name": "Mr. Andrea Marques de Almeida",
      "age": 54,
      "title": "VP of Finance & Investor Relations and Member of Executive Board",
      "yearBorn": 1971,
      "exercisedValue": 0,
      "unexercisedValue": 0
    },
    {
      "maxAge": 1,
      "name": "Mr. Marney Tadeu Antunes",
      "age": 63,
      "title": "Chief Distribution Officer & Member of Executive Board",
      "yearBorn": 1962,
      "exercisedValue": 0,
      "unexercisedValue": 0
    },
    {
      "maxAge": 1,
      "name": "Marco da Camino Ancona Lopez Soligo",
      "title": "VP of Generation & Broadcast and Member of Executive Board",
      "exercisedValue": 0,
      "unexercisedValue": 0
    },
    {
      "maxAge": 1,
      "name": "Mr. Sergio Lopes Cabral",
      "age": 60,
      "title": "VP of Commercialization & Member of Executive Board",
      "yearBorn": 1965,
      "exercisedValue": 0,
      "unexercisedValue": 0
    },
    {
      "maxAge": 1,
      "name": "S\u00e9rgio Pessoa de Paula Castro",
      "title": "VP of Legal Affairs & Member of Executive Board",
      "exercisedValue": 0,
      "unexercisedValue": 0
    },
    {
      "maxAge": 1,
      "name": "Marcos Montes Cordeiro",
      "title": "VP of Institutional Relations & Member of Executive Board",
      "exercisedValue": 0,
      "unexercisedValue": 0
    },
    {
      "maxAge": 1,
      "name": "Luis Cl\u00e1udio Correa Villani",
      "title": "Vice President of Information Technology & Member of Executive Board",
      "exercisedValue": 0,
      "unexercisedValue": 0
    },
    {
      "maxAge": 1,
      "name": "Mr. Paulo Eduardo Pereira Guimar\u00e3es",
      "title": "Head of Corporate Finance",
      "exercisedValue": 0,
      "unexercisedValue": 0
    },
    {
      "maxAge": 1,
      "name": "Daniel Perrelli Lanca",
      "title": "Deputy Director of Compliance, Corporate Risks & Internal Controls",
      "exercisedValue": 0,
      "unexercisedValue": 0
    }
  ],
  "auditRisk": 1,
  "boardRisk": 3,
  "compensationRisk": 1,
  "shareHolderRightsRisk": 9,
  "overallRisk": 2,
  "governanceEpochDate": 1772323200,
  "executiveTeam": [],
  "maxAge": 86400,
  "priceHint": 2,
  "previousClose": 12.32,
  "open": 0.0,
  "dayLow": 0.0,
  "dayHigh": 0.0,
  "regularMarketPreviousClose": 12.32,
  "regularMarketOpen": 0.0,
  "regularMarketDayLow": 0.0,
  "regularMarketDayHigh": 0.0,
  "dividendRate": 1.88,
  "dividendYield": 15.26,
  "exDividendDate": 1774396800,
  "payoutRatio": 0.96529996,
  "fiveYearAvgDividendYield": 9.05,
  "beta": 0.312,
  "trailingPE": 7.1988306,
  "forwardPE": 10.255513,
  "volume": 0,
  "regularMarketVolume": 0,
  "averageVolume": 13495413,
  "averageVolume10days": 15690940,
  "averageDailyVolume10Day": 15690940,
  "bid": 12.27,
  "ask": 12.31,
  "bidSize": 0,
  "askSize": 0,
  "marketCap": 38832529408,
  "nonDilutedMarketCap": 39356988447,
  "fiftyTwoWeekLow": 0.0,
  "fiftyTwoWeekHigh": 12.62,
  "allTimeHigh": 30902.287,
  "allTimeLow": 2.025908,
  "priceToSalesTrailing12Months": 0.908336,
  "fiftyDayAverage": 11.7772,
  "twoHundredDayAverage": 11.1759,
  "trailingAnnualDividendRate": 1.228,
  "trailingAnnualDividendYield": 0.09967533,
  "currency": "BRL",
  "tradeable": false,
  "enterpriseValue": 52441538560,
  "profitMargins": 0.11456,
  "floatShares": 2373107263,
  "sharesOutstanding": 1904080104,
  "heldPercentInsiders": 1.0000001e-05,
  "heldPercentInstitutions": 0.88253,
  "impliedSharesOutstanding": 3154551345,
  "bookValue": 9.989,
  "priceToBook": 1.2323556,
  "lastFiscalYearEnd": 1767139200,
  "nextFiscalYearEnd": 1798675200,
  "mostRecentQuarter": 1767139200,
  "earningsQuarterlyGrowth": 0.881,
  "netIncomeToCommon": 4897409024,
  "trailingEps": 1.71,
  "forwardEps": 1.20033,
  "lastSplitFactor": "130:100",
  "lastSplitDate": 1714435200,
  "enterpriseToRevenue": 1.227,
  "enterpriseToEbitda": 6.687,
  "52WeekChange": 0.22101092,
  "SandP52WeekChange": 0.1261568,
  "lastDividendValue": 0.23,
  "lastDividendDate": 1774396800,
  "quoteType": "EQUITY",
  "currentPrice": 12.31,
  "targetHighPrice": 13.8,
  "targetLowPrice": 9.2,
  "targetMeanPrice": 12.15583,
  "targetMedianPrice": 12.25,
  "recommendationMean": 3.23077,
  "recommendationKey": "hold",
  "numberOfAnalystOpinions": 12,
  "totalCash": 2661338112,
  "totalCashPerShare": 0.93,
  "ebitda": 7842365952,
  "totalDebt": 19882559488,
  "quickRatio": 0.778,
  "currentRatio": 1.001,
  "totalRevenue": 42751283200,
  "debtToEquity": 69.564,
  "revenuePerShare": 14.944,
  "returnOnAssets": 0.06287,
  "returnOnEquity": 0.1751,
  "grossProfits": 5341800960,
  "freeCashflow": -3585386240,
  "operatingCashflow": 4076534016,
  "earningsGrowth": 0.881,
  "revenueGrowth": 0.029,
  "grossMargins": 0.12495,
  "ebitdaMargins": 0.18344,
  "operatingMargins": 0.20073,
  "financialCurrency": "BRL",
  "symbol": "CMIG4.SA",
  "language": "en-US",
  "region": "US",
  "typeDisp": "Equity",
  "quoteSourceName": "Delayed Quote",
  "triggerable": false,
  "customPriceAlertConfidence": "LOW",
  "corporateActions": [],
  "regularMarketTime": 1774901277,
  "exchange": "SAO",
  "messageBoardId": "finmb_411574",
  "exchangeTimezoneName": "America/Sao_Paulo",
  "exchangeTimezoneShortName": "BRT",
  "gmtOffSetMilliseconds": -10800000,
  "market": "br_market",
  "esgPopulated": false,
  "regularMarketChangePercent": -0.08116295,
  "regularMarketPrice": 12.31,
  "longName": "Companhia Energ\u00e9tica de Minas Gerais - CEMIG",
  "marketState": "PREPRE",
  "shortName": "CEMIG       PN  EJ  N1",
  "hasPrePostMarketData": false,
  "firstTradeDateMilliseconds": 946900800000,
  "regularMarketChange": -0.009999275,
  "regularMarketDayRange": "0.0 - 0.0",
  "fullExchangeName": "S\u00e3o Paulo",
  "averageDailyVolume3Month": 13495413,
  "fiftyTwoWeekLowChange": 12.31,
  "fiftyTwoWeekRange": "0.0 - 12.62",
  "fiftyTwoWeekHighChange": -0.30999947,
  "fiftyTwoWeekHighChangePercent": -0.024564141,
  "fiftyTwoWeekChangePercent": 22.101093,
  "earningsTimestamp": 1773950400,
  "earningsTimestampStart": 1778184000,
  "earningsTimestampEnd": 1778184000,
  "earningsCallTimestampStart": 1774015200,
  "earningsCallTimestampEnd": 1774015200,
  "isEarningsDateEstimate": true,
  "epsForward": 1.20033,
  "epsTrailingTwelveMonths": 1.71,
  "epsCurrentYear": 1.34773,
  "priceEpsCurrentYear": 9.133877,
  "fiftyDayAverageChange": 0.5328007,
  "fiftyDayAverageChangePercent": 0.045240015,
  "twoHundredDayAverageChange": 1.1341,
  "twoHundredDayAverageChangePercent": 0.10147728,
  "sourceInterval": 15,
  "exchangeDataDelayedBy": 15,
  "prevName": "Companhia Energ\u00e9tica de Minas Gerais",
  "nameChangeDate": "2026-03-30",
  "averageAnalystRating": "3.2 - Hold",
  "cryptoTradeable": false,
  "trailingPegRatio": null
}