{
  "address1": "Rua dos Otoni, 177",
  "address2": "14th floor",
  "city": "Belo Horizonte",
  "state": "MG",
  "zip": "30150-270",
  "country": "Brazil",
  "website": "https://direcional.com.br",
  "industry": "Real Estate - Development",
  "industryKey": "real-estate-development",
  "industryDisp": "Real Estate - Development",
  "sector": "Real Estate",
  "sectorKey": "real-estate",
  "sectorDisp": "Real Estate",
  "longBusinessSummary": "Direcional Engenharia S.A. engages in the development and construction of affordable and mid-range residential real estate projects primarily in Brazil. The company focuses on the development, construction, and sale of housing units for low-income and middle-income families. The company was founded in 1981 and is based in Belo Horizonte, Brazil.",
  "companyOfficers": [
    {
      "maxAge": 1,
      "name": "Mr. Ricardo Ribeiro Valadares Gontijo",
      "age": 44,
      "title": "CEO, Member of Board of Executive Officers & Director",
      "yearBorn": 1981,
      "exercisedValue": 0,
      "unexercisedValue": 0
    },
    {
      "maxAge": 1,
      "name": "Mr. Paulo Henrique Martins De Sousa",
      "title": "Chief Financial and IR Officer & Member of Board of Executive Officers",
      "exercisedValue": 0,
      "unexercisedValue": 0
    },
    {
      "maxAge": 1,
      "name": "Ms. Laura Ribeiro Henriques",
      "title": "Chief Legal Officer & Member of Board of Executive Officers",
      "exercisedValue": 0,
      "unexercisedValue": 0
    },
    {
      "maxAge": 1,
      "name": "Mr. Guilherme  de Rezende Castanheira",
      "title": "Production Engineering Officer & Member of Board of Executive Officers",
      "exercisedValue": 0,
      "unexercisedValue": 0
    },
    {
      "maxAge": 1,
      "name": "Mr. Rafael Passos Valadares",
      "title": "Technical Engineering Officer & Member of Board of Executive Officers",
      "exercisedValue": 0,
      "unexercisedValue": 0
    },
    {
      "maxAge": 1,
      "name": "Mr. Jo\u00e3o Adriano Ponciano Nobre",
      "title": "Sales Officer & Member of Board of Executive Officers",
      "exercisedValue": 0,
      "unexercisedValue": 0
    },
    {
      "maxAge": 1,
      "name": "Mr. Eduardo Ferreira Quintella",
      "title": "Member of the Executive Board",
      "exercisedValue": 0,
      "unexercisedValue": 0
    },
    {
      "maxAge": 1,
      "name": "Ms. Ana Carolina Ribeiro Valadares Gontijo",
      "age": 43,
      "title": "Manager of Corporate Finance & Director",
      "yearBorn": 1982,
      "exercisedValue": 0,
      "unexercisedValue": 0
    },
    {
      "maxAge": 1,
      "name": "Mr. Giovanni Bruno Oliveira Costa Castilho",
      "title": "Secretary",
      "exercisedValue": 0,
      "unexercisedValue": 0
    },
    {
      "maxAge": 1,
      "name": "Andre  Damiao",
      "title": "Investor Relations Coordinator",
      "exercisedValue": 0,
      "unexercisedValue": 0
    }
  ],
  "auditRisk": 7,
  "boardRisk": 6,
  "compensationRisk": 6,
  "shareHolderRightsRisk": 5,
  "overallRisk": 6,
  "governanceEpochDate": 1780531200,
  "executiveTeam": [],
  "maxAge": 86400,
  "priceHint": 2,
  "previousClose": 13.55,
  "open": 13.24,
  "dayLow": 13.24,
  "dayHigh": 13.96,
  "regularMarketPreviousClose": 13.55,
  "regularMarketOpen": 13.24,
  "regularMarketDayLow": 13.24,
  "regularMarketDayHigh": 13.96,
  "dividendRate": 2.64,
  "dividendYield": 19.48,
  "exDividendDate": 1765929600,
  "payoutRatio": 1.3941001,
  "fiveYearAvgDividendYield": 6.95,
  "beta": 0.25,
  "trailingPE": 8.452829,
  "forwardPE": 5.9469023,
  "volume": 9575900,
  "regularMarketVolume": 9575900,
  "averageVolume": 7638395,
  "averageVolume10days": 6885444,
  "averageDailyVolume10Day": 6885444,
  "bid": 13.27,
  "ask": 13.48,
  "bidSize": 0,
  "askSize": 0,
  "marketCap": 6993295872,
  "nonDilutedMarketCap": 7050532759,
  "fiftyTwoWeekLow": 12.15,
  "fiftyTwoWeekHigh": 19.04,
  "allTimeHigh": 19.04,
  "allTimeLow": 0.999198,
  "priceToSalesTrailing12Months": 1.5158648,
  "fiftyDayAverage": 13.38,
  "twoHundredDayAverage": 14.97185,
  "trailingAnnualDividendRate": 0.0,
  "trailingAnnualDividendYield": 0.0,
  "currency": "BRL",
  "tradeable": false,
  "enterpriseValue": 8307029504,
  "profitMargins": 0.18164,
  "floatShares": 332150362,
  "sharesOutstanding": 520334521,
  "heldPercentInsiders": 0.28026,
  "heldPercentInstitutions": 0.46986,
  "impliedSharesOutstanding": 520334521,
  "bookValue": 3.693,
  "priceToBook": 3.6393175,
  "lastFiscalYearEnd": 1767139200,
  "nextFiscalYearEnd": 1798675200,
  "mostRecentQuarter": 1774915200,
  "earningsQuarterlyGrowth": 0.296,
  "netIncomeToCommon": 837985984,
  "trailingEps": 1.59,
  "forwardEps": 2.26,
  "lastSplitFactor": "3:1",
  "lastSplitDate": 1754870400,
  "enterpriseToRevenue": 1.801,
  "enterpriseToEbitda": 7.172,
  "52WeekChange": -0.007810533,
  "SandP52WeekChange": 0.23177934,
  "lastDividendValue": 1.55,
  "lastDividendDate": 1765929600,
  "quoteType": "EQUITY",
  "currentPrice": 13.44,
  "targetHighPrice": 23.0,
  "targetLowPrice": 16.5,
  "targetMeanPrice": 19.79167,
  "targetMedianPrice": 20.0,
  "recommendationMean": 1.25,
  "recommendationKey": "strong_buy",
  "numberOfAnalystOpinions": 12,
  "totalCash": 2420762112,
  "totalCashPerShare": 4.652,
  "ebitda": 1158301952,
  "totalDebt": 3313686016,
  "quickRatio": 2.839,
  "currentRatio": 4.257,
  "totalRevenue": 4613403136,
  "debtToEquity": 129.941,
  "revenuePerShare": 8.878,
  "returnOnAssets": 0.055170003,
  "returnOnEquity": 0.42945,
  "grossProfits": 1850547968,
  "freeCashflow": -424206496,
  "operatingCashflow": 432560000,
  "earningsGrowth": 0.29,
  "revenueGrowth": 0.302,
  "grossMargins": 0.40112,
  "ebitdaMargins": 0.25107,
  "operatingMargins": 0.2373,
  "financialCurrency": "BRL",
  "symbol": "DIRR3.SA",
  "language": "en-US",
  "region": "US",
  "typeDisp": "Equity",
  "quoteSourceName": "Delayed Quote",
  "triggerable": false,
  "customPriceAlertConfidence": "LOW",
  "corporateActions": [],
  "regularMarketTime": 1781294756,
  "exchange": "SAO",
  "messageBoardId": "finmb_45986509",
  "exchangeTimezoneName": "America/Sao_Paulo",
  "exchangeTimezoneShortName": "BRT",
  "gmtOffSetMilliseconds": -10800000,
  "market": "br_market",
  "esgPopulated": false,
  "regularMarketChangePercent": -0.81181264,
  "regularMarketPrice": 13.44,
  "marketState": "CLOSED",
  "longName": "Direcional Engenharia S.A.",
  "hasPrePostMarketData": false,
  "firstTradeDateMilliseconds": 1258632000000,
  "regularMarketChange": -0.11000061,
  "regularMarketDayRange": "13.24 - 13.96",
  "fullExchangeName": "S\u00e3o Paulo",
  "averageDailyVolume3Month": 7638395,
  "fiftyTwoWeekLowChange": 1.29,
  "fiftyTwoWeekLowChangePercent": 0.10617284,
  "fiftyTwoWeekRange": "12.15 - 19.04",
  "fiftyTwoWeekHighChange": -5.6000013,
  "fiftyTwoWeekHighChangePercent": -0.2941177,
  "fiftyTwoWeekChangePercent": -0.7810533,
  "earningsTimestampStart": 1754938800,
  "earningsTimestampEnd": 1754938800,
  "earningsCallTimestampStart": 1762858740,
  "earningsCallTimestampEnd": 1762858740,
  "isEarningsDateEstimate": false,
  "epsTrailingTwelveMonths": 1.59,
  "epsForward": 2.26,
  "epsCurrentYear": 1.94333,
  "priceEpsCurrentYear": 6.9159636,
  "cryptoTradeable": false,
  "fiftyDayAverageChange": 0.059999466,
  "fiftyDayAverageChangePercent": 0.004484265,
  "twoHundredDayAverageChange": -1.5318508,
  "twoHundredDayAverageChangePercent": -0.102315396,
  "sourceInterval": 15,
  "exchangeDataDelayedBy": 15,
  "averageAnalystRating": "1.3 - Strong Buy",
  "shortName": "DIRECIONAL  ON      NM",
  "trailingPegRatio": null
}