{
  "address1": "Avenida Morumbi",
  "address2": "8860 \u2013 8\u00ba andar Brooklin",
  "city": "S\u00e3o Paulo",
  "state": "SP",
  "zip": "04703-003",
  "country": "Brazil",
  "phone": "55 11 5014 7236",
  "website": "https://ri.fleury.com.br",
  "industry": "Diagnostics & Research",
  "industryKey": "diagnostics-research",
  "industryDisp": "Diagnostics & Research",
  "sector": "Healthcare",
  "sectorKey": "healthcare",
  "sectorDisp": "Healthcare",
  "longBusinessSummary": "Fleury S.A., together with its subsidiaries, provides diagnostic imaging, clinical analysis, fertility, and infusions services in Brazil. It operates in two segments, Diagnostic Medicine and Integrated Medicine. The company also provides health management services, such as telemedicine; orthopedic medicine services; laboratory support; toxicological exam; preventive, integrated solutions, and clinical research in oncology; integrated solutions, research, development of processes and services in genomics; and laboratory analysis services. In addition, it operates a health platform, immunobiological drug infusion center, and ophthalmology service centers. Fleury S.A. was founded in 1926 and is headquartered in S\u00e3o Paulo, Brazil.",
  "fullTimeEmployees": 28000,
  "companyOfficers": [
    {
      "maxAge": 1,
      "name": "Ms. Jeane Mike Tsutsui",
      "title": "CEO & President of Executive Board",
      "exercisedValue": 0,
      "unexercisedValue": 0
    },
    {
      "maxAge": 1,
      "name": "Mr. Jose Antonio de Almeida Filippo",
      "age": 65,
      "title": "CFO & Member of Executive Board",
      "yearBorn": 1960,
      "exercisedValue": 0,
      "unexercisedValue": 0
    },
    {
      "maxAge": 1,
      "name": "Mr. Edgar Gil Rizzatti",
      "title": "Medical, Technical & Process Executive Director and Member of Executive Board",
      "exercisedValue": 0,
      "unexercisedValue": 0
    },
    {
      "maxAge": 1,
      "name": "Mr. Roberto Santoro Meirelles",
      "title": "L2L & Operations Support Officer and Member of Executive Board",
      "exercisedValue": 0,
      "unexercisedValue": 0
    },
    {
      "maxAge": 1,
      "name": "Ms. Patricia Yumi Maeda Bertoncello",
      "title": "Executive Director of Service Units & Member of Executive Board",
      "exercisedValue": 0,
      "unexercisedValue": 0
    },
    {
      "maxAge": 1,
      "name": "Angelica Dente de Menezes",
      "title": "Secretary",
      "exercisedValue": 0,
      "unexercisedValue": 0
    },
    {
      "maxAge": 1,
      "name": "Mr. Renato  de Oliveira Braun",
      "title": "Investor Relations Director",
      "exercisedValue": 0,
      "unexercisedValue": 0
    }
  ],
  "auditRisk": 4,
  "boardRisk": 9,
  "compensationRisk": 9,
  "shareHolderRightsRisk": 1,
  "overallRisk": 9,
  "governanceEpochDate": 1775001600,
  "irWebsite": "http://ri.fleury.com.br/fleury/web/default_en.asp?idioma=1&conta=44",
  "executiveTeam": [],
  "maxAge": 86400,
  "priceHint": 2,
  "previousClose": 15.92,
  "open": 0.0,
  "dayLow": 0.0,
  "dayHigh": 0.0,
  "regularMarketPreviousClose": 15.92,
  "regularMarketOpen": 0.0,
  "regularMarketDayLow": 0.0,
  "regularMarketDayHigh": 0.0,
  "dividendRate": 1.89,
  "dividendYield": 11.87,
  "exDividendDate": 1764720000,
  "payoutRatio": 1.4958,
  "fiveYearAvgDividendYield": 4.95,
  "beta": 0.35,
  "trailingPE": 14.205357,
  "forwardPE": 10.9493065,
  "volume": 0,
  "regularMarketVolume": 0,
  "averageVolume": 3358032,
  "averageVolume10days": 3269240,
  "averageDailyVolume10Day": 3269240,
  "bid": 15.79,
  "ask": 15.92,
  "bidSize": 0,
  "askSize": 0,
  "marketCap": 8685666304,
  "nonDilutedMarketCap": 8669288682,
  "fiftyTwoWeekLow": 0.0,
  "fiftyTwoWeekHigh": 18.1,
  "allTimeHigh": 32.146446,
  "allTimeLow": 6.129419,
  "priceToSalesTrailing12Months": 1.0475788,
  "fiftyDayAverage": 16.5104,
  "twoHundredDayAverage": 15.251,
  "trailingAnnualDividendRate": 1.209,
  "trailingAnnualDividendYield": 0.07594221,
  "currency": "BRL",
  "tradeable": false,
  "enterpriseValue": 11880626176,
  "profitMargins": 0.07391,
  "floatShares": 210948238,
  "sharesOutstanding": 545924980,
  "heldPercentInsiders": 0.55294,
  "heldPercentInstitutions": 0.64825994,
  "impliedSharesOutstanding": 545924980,
  "bookValue": 9.177,
  "priceToBook": 1.733682,
  "lastFiscalYearEnd": 1767139200,
  "nextFiscalYearEnd": 1798675200,
  "mostRecentQuarter": 1767139200,
  "earningsQuarterlyGrowth": 0.148,
  "netIncomeToCommon": 612830976,
  "trailingEps": 1.12,
  "forwardEps": 1.45306,
  "lastSplitFactor": "21:20",
  "lastSplitDate": 1686614400,
  "enterpriseToRevenue": 1.433,
  "enterpriseToEbitda": 6.471,
  "52WeekChange": 0.38207138,
  "SandP52WeekChange": 0.32693863,
  "lastDividendValue": 0.899059,
  "lastDividendDate": 1764720000,
  "quoteType": "EQUITY",
  "currentPrice": 15.91,
  "targetHighPrice": 19.0,
  "targetLowPrice": 14.0,
  "targetMeanPrice": 17.48182,
  "targetMedianPrice": 18.0,
  "recommendationMean": 2.27273,
  "recommendationKey": "buy",
  "numberOfAnalystOpinions": 11,
  "totalCash": 2162391040,
  "totalCashPerShare": 3.968,
  "ebitda": 1835933952,
  "totalDebt": 5271442944,
  "quickRatio": 1.851,
  "currentRatio": 1.969,
  "totalRevenue": 8291182080,
  "debtToEquity": 103.437,
  "revenuePerShare": 15.215,
  "returnOnAssets": 0.0596,
  "returnOnEquity": 0.113970004,
  "grossProfits": 2206036992,
  "freeCashflow": 954625728,
  "operatingCashflow": 2133774976,
  "earningsGrowth": 0.146,
  "revenueGrowth": 0.12,
  "grossMargins": 0.26607,
  "ebitdaMargins": 0.22143,
  "operatingMargins": 0.1094,
  "financialCurrency": "BRL",
  "symbol": "FLRY3.SA",
  "language": "en-US",
  "region": "US",
  "typeDisp": "Equity",
  "quoteSourceName": "Delayed Quote",
  "triggerable": false,
  "customPriceAlertConfidence": "LOW",
  "shortName": "FLEURY      ON      NM",
  "longName": "Fleury S.A.",
  "cryptoTradeable": false,
  "marketState": "PREPRE",
  "hasPrePostMarketData": false,
  "firstTradeDateMilliseconds": 1261051200000,
  "regularMarketChange": -0.010000229,
  "regularMarketDayRange": "0.0 - 0.0",
  "fullExchangeName": "S\u00e3o Paulo",
  "averageDailyVolume3Month": 3358032,
  "fiftyTwoWeekLowChange": 15.91,
  "fiftyTwoWeekRange": "0.0 - 18.1",
  "fiftyTwoWeekHighChange": -2.1900005,
  "fiftyTwoWeekHighChangePercent": -0.1209945,
  "fiftyTwoWeekChangePercent": 38.207138,
  "earningsTimestamp": 1778184000,
  "earningsTimestampStart": 1778184000,
  "earningsTimestampEnd": 1778184000,
  "earningsCallTimestampStart": 1772805600,
  "earningsCallTimestampEnd": 1772805600,
  "isEarningsDateEstimate": false,
  "epsTrailingTwelveMonths": 1.12,
  "epsForward": 1.45306,
  "epsCurrentYear": 1.26865,
  "priceEpsCurrentYear": 12.540889,
  "fiftyDayAverageChange": -0.6004009,
  "fiftyDayAverageChangePercent": -0.036365014,
  "twoHundredDayAverageChange": 0.65899944,
  "twoHundredDayAverageChangePercent": 0.043210242,
  "sourceInterval": 15,
  "exchangeDataDelayedBy": 15,
  "averageAnalystRating": "2.3 - Buy",
  "corporateActions": [],
  "regularMarketTime": 1775592468,
  "exchange": "SAO",
  "messageBoardId": "finmb_22988815",
  "exchangeTimezoneName": "America/Sao_Paulo",
  "exchangeTimezoneShortName": "BRT",
  "gmtOffSetMilliseconds": -10800000,
  "market": "br_market",
  "esgPopulated": false,
  "regularMarketChangePercent": -0.06281551,
  "regularMarketPrice": 15.91,
  "trailingPegRatio": null
}