{
  "address1": "Av. Magalh\u00e3es de Castro, 4800",
  "address2": "240 Floor Continental Tower Building Bairro Cidade Jardim",
  "city": "S\u00e3o Paulo",
  "state": "SP",
  "zip": "05676-120",
  "country": "Brazil",
  "website": "https://www.hypera.com.br",
  "industry": "Drug Manufacturers - Specialty & Generic",
  "industryKey": "drug-manufacturers-specialty-generic",
  "industryDisp": "Drug Manufacturers - Specialty & Generic",
  "sector": "Healthcare",
  "sectorKey": "healthcare",
  "sectorDisp": "Healthcare",
  "longBusinessSummary": "Hypera S.A. operates as a pharmaceutical company in Brazil. The company provides sweeteners products under the Adocyl, finn, and Zero-cal brands; analgesics and anti-inflammatories products under the Doril, Atroveran, Calminex, Alivium, Buscopan, Buscofem, geloll, Torsilax, Neosaldina, and naprohax brands; cold and flu remedies and decongestants products under BENEGRIO, Rinosoro, Blu, Neosoro, Coristina, APRACUR, and Fluviral brands. It offers antihistamines products under Alektos, Histamin, Polaramine, PredSim, and Desrinite brands; antiseptics products under Merthiolate brand; Herbal medicine products under Maracugina, Eparema, Tamarine, and Naturetti brands; gastrointestinal products under Dramin, Estomazil, Engov, Lacto-purga, gastrol, Epocler, Bifilax, and Pepsamar brands. In addition, the company provides generics products under neo quimica brand; skicare products under episol, epidrat, simple organic, and bioage brands; supplements and vitamins products Addera, Biotonico Fontoura, Colflex, and Vitasay brands; and other products under Nebacetin, Cepacol, ESCABIN, Mirrorelax, Ammy, Nesina, and Diprospan brands. The company was formerly known as Hypermarcas S.A. and changed its name to Hypera S.A. in February 2018. Hypera S.A. was founded in 1999 and is headquartered in S\u00e3o Paulo, Brazil.",
  "fullTimeEmployees": 10564,
  "companyOfficers": [
    {
      "maxAge": 1,
      "name": "Mr. Breno Toledo Pires de Oliveira",
      "age": 50,
      "title": "Chief Executive Officer",
      "yearBorn": 1975,
      "exercisedValue": 0,
      "unexercisedValue": 0
    },
    {
      "maxAge": 1,
      "name": "Mr. Ramon Sanches Frutuoso Silva",
      "age": 38,
      "title": "CFO & Investor Relation Officer",
      "yearBorn": 1987,
      "exercisedValue": 0,
      "unexercisedValue": 0
    },
    {
      "maxAge": 1,
      "name": "Mr. Rafael Vito Batista",
      "age": 40,
      "title": "Chief Operations Officer",
      "yearBorn": 1985,
      "exercisedValue": 0,
      "unexercisedValue": 0
    },
    {
      "maxAge": 1,
      "name": "Mr. Luiz Eduardo Sales Clavis",
      "age": 54,
      "title": "Vice President of Commercial & Marketing",
      "yearBorn": 1971,
      "exercisedValue": 0,
      "unexercisedValue": 0
    },
    {
      "maxAge": 1,
      "name": "Mauricio  Christovam",
      "title": "Senior Human Resources Officer",
      "exercisedValue": 0,
      "unexercisedValue": 0
    },
    {
      "maxAge": 1,
      "name": "Mr. H\u00e9lio  Segouras",
      "title": "Head of Consumer Health",
      "exercisedValue": 0,
      "unexercisedValue": 0
    }
  ],
  "auditRisk": 1,
  "boardRisk": 7,
  "compensationRisk": 6,
  "shareHolderRightsRisk": 1,
  "overallRisk": 6,
  "governanceEpochDate": 1775001600,
  "irWebsite": "http://hypermarcas.infoinvest.com.br/?idioma=enu",
  "executiveTeam": [],
  "maxAge": 86400,
  "priceHint": 2,
  "previousClose": 22.54,
  "open": 0.0,
  "dayLow": 0.0,
  "dayHigh": 0.0,
  "regularMarketPreviousClose": 22.54,
  "regularMarketOpen": 0.0,
  "regularMarketDayLow": 0.0,
  "regularMarketDayHigh": 0.0,
  "dividendRate": 1.05,
  "dividendYield": 4.67,
  "exDividendDate": 1775001600,
  "payoutRatio": 0.62259996,
  "fiveYearAvgDividendYield": 4.01,
  "beta": 0.168,
  "trailingPE": 12.144384,
  "forwardPE": 6.835708,
  "volume": 0,
  "regularMarketVolume": 0,
  "averageVolume": 3175803,
  "averageVolume10days": 2776980,
  "averageDailyVolume10Day": 2776980,
  "bid": 22.51,
  "ask": 22.79,
  "bidSize": 0,
  "askSize": 0,
  "marketCap": 15976528896,
  "nonDilutedMarketCap": 15856934381,
  "fiftyTwoWeekLow": 0.0,
  "fiftyTwoWeekHigh": 28.87,
  "allTimeHigh": 51.11,
  "allTimeLow": 4.55,
  "priceToSalesTrailing12Months": 2.0751011,
  "fiftyDayAverage": 22.877,
  "twoHundredDayAverage": 23.8039,
  "trailingAnnualDividendRate": 1.17,
  "trailingAnnualDividendYield": 0.051907714,
  "currency": "BRL",
  "tradeable": false,
  "enterpriseValue": 22247483392,
  "profitMargins": 0.15526,
  "floatShares": 252871258,
  "sharesOutstanding": 703501969,
  "heldPercentInsiders": 0.47859,
  "heldPercentInstitutions": 0.35389,
  "impliedSharesOutstanding": 703501969,
  "bookValue": 19.783,
  "priceToBook": 1.1479552,
  "lastFiscalYearEnd": 1767139200,
  "nextFiscalYearEnd": 1798675200,
  "mostRecentQuarter": 1767139200,
  "earningsQuarterlyGrowth": 4.669,
  "netIncomeToCommon": 1196064000,
  "trailingEps": 1.87,
  "forwardEps": 3.32226,
  "pegRatio": 0.76,
  "lastSplitFactor": "2:1",
  "lastSplitDate": 1262563200,
  "enterpriseToRevenue": 2.89,
  "enterpriseToEbitda": 11.386,
  "52WeekChange": -0.033447683,
  "SandP52WeekChange": 0.290079,
  "lastDividendValue": 0.26304,
  "lastDividendDate": 1775001600,
  "quoteType": "EQUITY",
  "currentPrice": 22.71,
  "targetHighPrice": 35.0,
  "targetLowPrice": 24.5,
  "targetMeanPrice": 29.34615,
  "targetMedianPrice": 29.5,
  "recommendationMean": 2.07692,
  "recommendationKey": "buy",
  "numberOfAnalystOpinions": 13,
  "totalCash": 1645540992,
  "totalCashPerShare": 2.6,
  "ebitda": 1953874048,
  "totalDebt": 9516306432,
  "quickRatio": 0.907,
  "currentRatio": 1.471,
  "totalRevenue": 7699156992,
  "debtToEquity": 75.982,
  "revenuePerShare": 12.17,
  "returnOnAssets": 0.043909997,
  "returnOnEquity": 0.09671,
  "grossProfits": 4545506816,
  "freeCashflow": 764288256,
  "operatingCashflow": 2574430976,
  "earningsGrowth": 4.436,
  "revenueGrowth": 0.481,
  "grossMargins": 0.59039,
  "ebitdaMargins": 0.25378,
  "operatingMargins": 0.29027998,
  "financialCurrency": "BRL",
  "symbol": "HYPE3.SA",
  "language": "en-US",
  "region": "US",
  "typeDisp": "Equity",
  "quoteSourceName": "Delayed Quote",
  "triggerable": false,
  "customPriceAlertConfidence": "LOW",
  "regularMarketChange": 0.16999817,
  "regularMarketDayRange": "0.0 - 0.0",
  "fullExchangeName": "S\u00e3o Paulo",
  "averageDailyVolume3Month": 3175803,
  "fiftyTwoWeekLowChange": 22.71,
  "fiftyTwoWeekRange": "0.0 - 28.87",
  "fiftyTwoWeekHighChange": -6.1600018,
  "fiftyTwoWeekHighChangePercent": -0.21337034,
  "fiftyTwoWeekChangePercent": -3.3447683,
  "earningsTimestamp": 1777406400,
  "earningsTimestampStart": 1777406400,
  "earningsTimestampEnd": 1777406400,
  "earningsCallTimestampStart": 1777471200,
  "earningsCallTimestampEnd": 1777471200,
  "isEarningsDateEstimate": false,
  "epsTrailingTwelveMonths": 1.87,
  "epsForward": 3.32226,
  "epsCurrentYear": 2.77253,
  "priceEpsCurrentYear": 8.191074,
  "fiftyDayAverageChange": -0.16700172,
  "fiftyDayAverageChangePercent": -0.0072999834,
  "twoHundredDayAverageChange": -1.0939007,
  "twoHundredDayAverageChangePercent": -0.045954682,
  "sourceInterval": 15,
  "exchangeDataDelayedBy": 15,
  "averageAnalystRating": "2.1 - Buy",
  "corporateActions": [],
  "regularMarketTime": 1777320450,
  "regularMarketChangePercent": 0.7542066,
  "regularMarketPrice": 22.71,
  "shortName": "HYPERA      ON      NM",
  "exchange": "SAO",
  "messageBoardId": "finmb_34669017",
  "exchangeTimezoneName": "America/Sao_Paulo",
  "exchangeTimezoneShortName": "BRT",
  "gmtOffSetMilliseconds": -10800000,
  "market": "br_market",
  "esgPopulated": false,
  "longName": "Hypera S.A.",
  "marketState": "PREPRE",
  "cryptoTradeable": false,
  "hasPrePostMarketData": false,
  "firstTradeDateMilliseconds": 1208523600000,
  "trailingPegRatio": null
}