{
  "address1": "Brigadeiro Lu\u00eds Ant\u00f4nio Avenue, 1343",
  "address2": "9th Floor Bela Vista",
  "city": "S\u00e3o Paulo",
  "state": "SP",
  "zip": "01317-910",
  "country": "Brazil",
  "phone": "55 11 3177 7014",
  "website": "https://www.ultra.com.br",
  "industry": "Oil & Gas Refining & Marketing",
  "industryKey": "oil-gas-refining-marketing",
  "industryDisp": "Oil & Gas Refining & Marketing",
  "sector": "Energy",
  "sectorKey": "energy",
  "sectorDisp": "Energy",
  "longBusinessSummary": "Ultrapar Participa\u00e7\u00f5es S.A., through its subsidiaries, operates in the energy, mobility, and logistics infrastructure sectors in Brazil, the rest of Europe, the United States, Canada, other Latin American countries, Oceania, and internationally. It operates through Ultragaz, Ipiranga, Ultracargo, and Hidrovias segments. The company distributes and sells oil-related products, biofuels, gasoline, ethanol, diesel, fuel oil, kerosene, natural gas for vehicles, and additive fuels under the Ipimax brand to carriers, resellers, and retailers; operates service stations under the Ipiranga brand and convenience stores under the AmPm brand; and produces and sells lubricants under the ICONIC brand. It also engages in the distribution of bulk and bottled liquefied petroleum gas for the residential, condominium, trade, services, industrial, and agribusiness sectors; operation of a natural gas pipeline network; and provision of renewable electricity for businesses and households, as well as compressed natural gas and biomethane for corporate clients. In addition, the company operates liquid bulk storage terminals in logistics centers; waterway and multimodal infrastructure; and port operations. Further, the company offers logistics solutions for handling grains, ores, and fertilizers; automotive services through Jet Oil units; and loyalty programs under the Km de Vantagens (KMV) brand. It also exports its products and services. Ultrapar Participa\u00e7\u00f5es S.A. was founded in 1937 and is headquartered in S\u00e3o Paulo, Brazil.",
  "companyOfficers": [
    {
      "maxAge": 1,
      "name": "Mr. Rodrigo  de Almeida Pizzinatto",
      "age": 48,
      "title": "CEO & Member of Executive Board",
      "yearBorn": 1977,
      "exercisedValue": 0,
      "unexercisedValue": 0
    },
    {
      "maxAge": 1,
      "name": "Mr. Fulvius  Tomelin",
      "title": "President",
      "exercisedValue": 0,
      "unexercisedValue": 0
    },
    {
      "maxAge": 1,
      "name": "Mr. Alexandre Mendes Palhares",
      "age": 39,
      "title": "Chief Financial & Investor Relations Officer",
      "yearBorn": 1986,
      "exercisedValue": 0,
      "unexercisedValue": 0
    },
    {
      "maxAge": 1,
      "name": "Mr. Decio  de Sampaio Amaral",
      "age": 56,
      "title": "CEO of Hidrovias do Brasil & Member of Executive Board",
      "yearBorn": 1969,
      "exercisedValue": 0,
      "unexercisedValue": 0
    },
    {
      "maxAge": 1,
      "name": "Ms. Fernanda Teves de Souza",
      "title": "Risks, Compliance & Audit Director",
      "exercisedValue": 0,
      "unexercisedValue": 0
    }
  ],
  "auditRisk": 1,
  "boardRisk": 1,
  "compensationRisk": 6,
  "shareHolderRightsRisk": 1,
  "overallRisk": 1,
  "governanceEpochDate": 1775001600,
  "irWebsite": "http://www.ultra.com.br/ri/english/index.htm",
  "executiveTeam": [],
  "maxAge": 86400,
  "priceHint": 2,
  "previousClose": 29.15,
  "open": 0.0,
  "dayLow": 0.0,
  "dayHigh": 0.0,
  "regularMarketPreviousClose": 29.15,
  "regularMarketOpen": 0.0,
  "regularMarketDayLow": 0.0,
  "regularMarketDayHigh": 0.0,
  "dividendRate": 1.75,
  "dividendYield": 6.0,
  "exDividendDate": 1765152000,
  "payoutRatio": 0.7443,
  "fiveYearAvgDividendYield": 3.28,
  "beta": 0.417,
  "trailingPE": 12.531916,
  "forwardPE": 11.088353,
  "volume": 0,
  "regularMarketVolume": 0,
  "averageVolume": 6308189,
  "averageVolume10days": 4413780,
  "averageDailyVolume10Day": 4413780,
  "bid": 29.31,
  "ask": 29.6,
  "bidSize": 0,
  "askSize": 0,
  "marketCap": 31475197952,
  "nonDilutedMarketCap": 31154567348,
  "fiftyTwoWeekLow": 0.0,
  "fiftyTwoWeekHigh": 30.81,
  "allTimeHigh": 6427221.5,
  "allTimeLow": 2.884141,
  "priceToSalesTrailing12Months": 0.22108099,
  "fiftyDayAverage": 27.879,
  "twoHundredDayAverage": 22.63985,
  "trailingAnnualDividendRate": 0.0,
  "trailingAnnualDividendYield": 0.0,
  "currency": "BRL",
  "tradeable": false,
  "enterpriseValue": 48343773184,
  "profitMargins": 0.017239999,
  "floatShares": 645253118,
  "sharesOutstanding": 1068767319,
  "heldPercentInsiders": 0.32734,
  "heldPercentInstitutions": 0.42734,
  "impliedSharesOutstanding": 1068767319,
  "bookValue": 14.659,
  "priceToBook": 2.0090046,
  "lastFiscalYearEnd": 1767139200,
  "nextFiscalYearEnd": 1798675200,
  "mostRecentQuarter": 1767139200,
  "earningsQuarterlyGrowth": -0.616,
  "netIncomeToCommon": 2660165120,
  "trailingEps": 2.35,
  "forwardEps": 2.65594,
  "pegRatio": 0.78,
  "lastSplitFactor": "2:1",
  "lastSplitDate": 1555545600,
  "enterpriseToRevenue": 0.34,
  "enterpriseToEbitda": 7.576,
  "52WeekChange": 0.6348851,
  "SandP52WeekChange": 0.28186798,
  "lastDividendValue": 1.0,
  "lastDividendDate": 1765152000,
  "quoteType": "EQUITY",
  "currentPrice": 29.45,
  "targetHighPrice": 39.0,
  "targetLowPrice": 25.0,
  "targetMeanPrice": 31.25625,
  "targetMedianPrice": 31.3,
  "recommendationMean": 2.33333,
  "recommendationKey": "buy",
  "numberOfAnalystOpinions": 16,
  "totalCash": 7026883072,
  "totalCashPerShare": 6.575,
  "ebitda": 6381184000,
  "totalDebt": 21832894464,
  "quickRatio": 1.148,
  "currentRatio": 1.619,
  "totalRevenue": 142369538048,
  "debtToEquity": 123.137,
  "revenuePerShare": 132.841,
  "returnOnAssets": 0.06954,
  "returnOnEquity": 0.16381,
  "grossProfits": 9358840832,
  "freeCashflow": 1854222720,
  "operatingCashflow": 5452502016,
  "earningsGrowth": -0.595,
  "revenueGrowth": 0.072,
  "grossMargins": 0.06574,
  "ebitdaMargins": 0.04482,
  "operatingMargins": 0.03091,
  "financialCurrency": "BRL",
  "symbol": "UGPA3.SA",
  "language": "en-US",
  "region": "US",
  "typeDisp": "Equity",
  "quoteSourceName": "Delayed Quote",
  "triggerable": false,
  "customPriceAlertConfidence": "LOW",
  "epsTrailingTwelveMonths": 2.35,
  "epsForward": 2.65594,
  "epsCurrentYear": 2.23953,
  "priceEpsCurrentYear": 13.150081,
  "fiftyDayAverageChange": 1.571001,
  "fiftyDayAverageChangePercent": 0.056350697,
  "twoHundredDayAverageChange": 6.81015,
  "twoHundredDayAverageChangePercent": 0.30080366,
  "sourceInterval": 15,
  "exchangeDataDelayedBy": 15,
  "averageAnalystRating": "2.3 - Buy",
  "cryptoTradeable": false,
  "marketState": "PREPRE",
  "regularMarketChange": 0.30000114,
  "regularMarketDayRange": "0.0 - 0.0",
  "fullExchangeName": "S\u00e3o Paulo",
  "averageDailyVolume3Month": 6308189,
  "fiftyTwoWeekLowChange": 29.45,
  "fiftyTwoWeekRange": "0.0 - 30.81",
  "fiftyTwoWeekHighChange": -1.3599987,
  "fiftyTwoWeekHighChangePercent": -0.04414147,
  "fiftyTwoWeekChangePercent": 63.488506,
  "earningsTimestamp": 1778097600,
  "earningsTimestampStart": 1778097600,
  "earningsTimestampEnd": 1778097600,
  "earningsCallTimestampStart": 1778162400,
  "earningsCallTimestampEnd": 1778162400,
  "isEarningsDateEstimate": false,
  "shortName": "ULTRAPAR    ON      NM",
  "longName": "Ultrapar Participa\u00e7\u00f5es S.A.",
  "hasPrePostMarketData": false,
  "firstTradeDateMilliseconds": 1039608000000,
  "corporateActions": [],
  "regularMarketTime": 1777406871,
  "exchange": "SAO",
  "messageBoardId": "finmb_403623",
  "exchangeTimezoneName": "America/Sao_Paulo",
  "exchangeTimezoneShortName": "BRT",
  "gmtOffSetMilliseconds": -10800000,
  "market": "br_market",
  "esgPopulated": false,
  "regularMarketChangePercent": 1.0291634,
  "regularMarketPrice": 29.45,
  "trailingPegRatio": null
}