{
  "address1": "Avenida Prefeito Waldemar Grubba, 3300",
  "city": "Jaragu\u00e1 do Sul",
  "state": "SC",
  "zip": "89256-900",
  "country": "Brazil",
  "phone": "55 47 3276 4000",
  "website": "https://www.weg.net/institutional/BR/en/",
  "industry": "Electrical Equipment & Parts",
  "industryKey": "electrical-equipment-parts",
  "industryDisp": "Electrical Equipment & Parts",
  "sector": "Industrials",
  "sectorKey": "industrials",
  "sectorDisp": "Industrials",
  "longBusinessSummary": "WEG S.A. produces and sells capital goods in Brazil and internationally. The company offers electric motors, generators, and transformers; reducers and gearmotors; hydraulic and steam turbines; frequency converters, starters engines and switching devices; control and protection of electrical circuits for industrial automation; sockets and switches; and solutions for electric traction of heavy vehicles, utility and locomotives, and electric propulsion of naval transport. It also provides solutions for generating renewable and distributed energy, in small hydroelectric plants, biomass, wind and solar; solutions for industry; UPSs and alternators for generator sets; substations electrical, conventional and mobile; industrial electronic systems; industrial paints, varnishes, and paints for automotive repainting. WEG S.A. was founded in 1961 and is headquartered in Jaragu\u00e1 do Sul, Brazil.",
  "fullTimeEmployees": 49258,
  "companyOfficers": [
    {
      "maxAge": 1,
      "name": "Mr. Alberto Yoshikazu Kuba",
      "title": "CEO & Member of Executive Board",
      "exercisedValue": 0,
      "unexercisedValue": 0
    },
    {
      "maxAge": 1,
      "name": "Mr. Andre Luis Rodrigues",
      "title": "CFO, Administrative & Financial Director and Member of Executive Board",
      "exercisedValue": 0,
      "unexercisedValue": 0
    },
    {
      "maxAge": 1,
      "name": "Mr. Carlos Diether Prinz",
      "title": "Director of WEG T&D and Member of Executive Board",
      "exercisedValue": 0,
      "unexercisedValue": 0
    },
    {
      "maxAge": 1,
      "name": "Mr. Manfred Peter Johann",
      "title": "Director of Automation Division & Member of Executive Board",
      "exercisedValue": 0,
      "unexercisedValue": 0
    },
    {
      "maxAge": 1,
      "name": "Mr. Daniel Marteleto Godinho",
      "title": "Director of Sustainability & Institutional Relations and Member of Executive Board",
      "exercisedValue": 0,
      "unexercisedValue": 0
    },
    {
      "maxAge": 1,
      "name": "Mr. Andre Menegueti Salgueiro",
      "title": "Finance Director & Investor Relations Officer & Member of Executive Board",
      "exercisedValue": 0,
      "unexercisedValue": 0
    },
    {
      "maxAge": 1,
      "name": "Mr. Jo\u00e3o Paulo Gualberto da Silva",
      "title": "Director of WEG Energy & Member of Executive Board",
      "exercisedValue": 0,
      "unexercisedValue": 0
    },
    {
      "maxAge": 1,
      "name": "Mr. Julio Cesar Ramires",
      "title": "Director of Commercial Motors & Member of Executive Board",
      "exercisedValue": 0,
      "unexercisedValue": 0
    },
    {
      "maxAge": 1,
      "name": "Mr. Carlos Jose Bastos Grillo",
      "title": "VP of Technology & Member of Executive Board",
      "exercisedValue": 0,
      "unexercisedValue": 0
    },
    {
      "maxAge": 1,
      "name": "Ms. Juliano Saldanha Vargas",
      "title": "Executive Officer, Director of HR & Member of Executive Board",
      "exercisedValue": 0,
      "unexercisedValue": 0
    }
  ],
  "auditRisk": 3,
  "boardRisk": 9,
  "compensationRisk": 5,
  "shareHolderRightsRisk": 1,
  "overallRisk": 8,
  "governanceEpochDate": 1772323200,
  "executiveTeam": [],
  "maxAge": 86400,
  "priceHint": 2,
  "previousClose": 46.59,
  "open": 46.5,
  "dayLow": 45.44,
  "dayHigh": 46.53,
  "regularMarketPreviousClose": 46.59,
  "regularMarketOpen": 46.5,
  "regularMarketDayLow": 45.44,
  "regularMarketDayHigh": 46.53,
  "dividendRate": 0.4,
  "dividendYield": 0.87,
  "exDividendDate": 1774224000,
  "payoutRatio": 1.1888,
  "fiveYearAvgDividendYield": 1.03,
  "beta": 0.073,
  "trailingPE": 30.236841,
  "forwardPE": 23.361612,
  "volume": 10201200,
  "regularMarketVolume": 10201200,
  "averageVolume": 7236371,
  "averageVolume10days": 5935420,
  "averageDailyVolume10Day": 5935420,
  "bid": 46.0,
  "ask": 46.0,
  "bidSize": 0,
  "askSize": 0,
  "marketCap": 192834895872,
  "nonDilutedMarketCap": 192834898242,
  "fiftyTwoWeekLow": 35.25,
  "fiftyTwoWeekHigh": 54.53,
  "allTimeHigh": 59.83,
  "allTimeLow": 0.140532,
  "priceToSalesTrailing12Months": 4.725869,
  "fiftyDayAverage": 49.5664,
  "twoHundredDayAverage": 43.31775,
  "trailingAnnualDividendRate": 2.148,
  "trailingAnnualDividendYield": 0.046104316,
  "currency": "BRL",
  "tradeable": false,
  "enterpriseValue": 192128483328,
  "profitMargins": 0.15626,
  "floatShares": 1485947686,
  "sharesOutstanding": 4195711450,
  "heldPercentInsiders": 0.64559,
  "heldPercentInstitutions": 0.15581,
  "impliedSharesOutstanding": 4195711450,
  "bookValue": 4.151,
  "priceToBook": 11.072031,
  "lastFiscalYearEnd": 1767139200,
  "nextFiscalYearEnd": 1798675200,
  "mostRecentQuarter": 1767139200,
  "earningsQuarterlyGrowth": -0.063,
  "netIncomeToCommon": 6376219136,
  "trailingEps": 1.52,
  "forwardEps": 1.96733,
  "lastSplitFactor": "2:1",
  "lastSplitDate": 1619568000,
  "enterpriseToRevenue": 4.709,
  "enterpriseToEbitda": 21.914,
  "52WeekChange": -0.029560804,
  "SandP52WeekChange": 0.12811458,
  "lastDividendValue": 0.100121,
  "lastDividendDate": 1774224000,
  "quoteType": "EQUITY",
  "currentPrice": 45.96,
  "targetHighPrice": 70.0,
  "targetLowPrice": 39.0,
  "targetMeanPrice": 53.17143,
  "targetMedianPrice": 51.0,
  "recommendationMean": 2.71429,
  "recommendationKey": "hold",
  "numberOfAnalystOpinions": 14,
  "totalCash": 7279864832,
  "totalCashPerShare": 1.735,
  "ebitda": 8767263744,
  "totalDebt": 5437975040,
  "quickRatio": 0.926,
  "currentRatio": 1.548,
  "totalRevenue": 40804110336,
  "debtToEquity": 29.31,
  "revenuePerShare": 9.725,
  "returnOnAssets": 0.11845,
  "returnOnEquity": 0.32514998,
  "grossProfits": 13681633280,
  "freeCashflow": 3909349120,
  "operatingCashflow": 6451033088,
  "earningsGrowth": -0.063,
  "revenueGrowth": -0.053,
  "grossMargins": 0.3353,
  "ebitdaMargins": 0.21486,
  "operatingMargins": 0.19398001,
  "financialCurrency": "BRL",
  "symbol": "WEGE3.SA",
  "language": "en-US",
  "region": "US",
  "typeDisp": "Equity",
  "quoteSourceName": "Delayed Quote",
  "triggerable": false,
  "customPriceAlertConfidence": "LOW",
  "regularMarketChange": -0.63000107,
  "regularMarketDayRange": "45.44 - 46.53",
  "fullExchangeName": "S\u00e3o Paulo",
  "averageDailyVolume3Month": 7236371,
  "fiftyTwoWeekLowChange": 10.709999,
  "fiftyTwoWeekLowChangePercent": 0.30382976,
  "fiftyTwoWeekRange": "35.25 - 54.53",
  "fiftyTwoWeekHighChange": -8.57,
  "fiftyTwoWeekHighChangePercent": -0.15716119,
  "fiftyTwoWeekChangePercent": -2.9560804,
  "earningsTimestamp": 1777492800,
  "earningsTimestampStart": 1777492800,
  "earningsTimestampEnd": 1777492800,
  "earningsCallTimestampStart": 1772114400,
  "earningsCallTimestampEnd": 1772114400,
  "isEarningsDateEstimate": false,
  "epsTrailingTwelveMonths": 1.52,
  "epsForward": 1.96733,
  "epsCurrentYear": 1.65702,
  "corporateActions": [
    {
      "header": "Dividend",
      "message": "WEGE3.SA announced a cash dividend of BRL 0.10 with an ex-date of Mar. 23, 2026",
      "meta": {
        "eventType": "DIVIDEND",
        "dateEpochMs": 1774234800000,
        "amount": "0.10"
      }
    }
  ],
  "regularMarketTime": 1774037250,
  "exchange": "SAO",
  "messageBoardId": "finmb_879809",
  "exchangeTimezoneName": "America/Sao_Paulo",
  "exchangeTimezoneShortName": "BRT",
  "gmtOffSetMilliseconds": -10800000,
  "market": "br_market",
  "esgPopulated": false,
  "marketState": "CLOSED",
  "shortName": "WEG         ON      NM",
  "longName": "WEG S.A.",
  "regularMarketChangePercent": -1.3522238,
  "regularMarketPrice": 45.96,
  "hasPrePostMarketData": false,
  "firstTradeDateMilliseconds": 946900800000,
  "priceEpsCurrentYear": 27.73654,
  "fiftyDayAverageChange": -3.6063995,
  "fiftyDayAverageChangePercent": -0.07275896,
  "twoHundredDayAverageChange": 2.64225,
  "twoHundredDayAverageChangePercent": 0.06099694,
  "sourceInterval": 15,
  "exchangeDataDelayedBy": 15,
  "averageAnalystRating": "2.7 - Hold",
  "cryptoTradeable": false,
  "trailingPegRatio": null
}